pyoppleio/Message.py
pyoppleio/OppleDevice.py
pyoppleio/OppleLightDevice.py
pyoppleio/__init__.py
pyoppleio/__main__.py
pyoppleio/const.py
pyoppleio_310-1.0.8.dist-info/LICENSE
pyoppleio_310-1.0.8.dist-info/METADATA
pyoppleio_310-1.0.8.dist-info/WHEEL
pyoppleio_310-1.0.8.dist-info/entry_points.txt
pyoppleio_310-1.0.8.dist-info/top_level.txt
pyoppleio_310-1.0.8.dist-info/RECORD
