Metadata-Version: 2.1
Name: pyoppleio-310
Version: 1.0.8
Summary: Python library for interfacing with opple mobile control light for python 3.10+
Home-page: https://github.com/tinysnake/python-oppleio-py310
Author: tinysnake
Author-email: tff.assist@live.com
License: MIT
Keywords: opple,iot
Platform: any
Requires-Python: >=3.10
License-File: LICENSE
Requires-Dist: pycrc16 (==0.1.2)
